{"city":{"lang":"en","cityName":"Cuernavaca","cityLatitude":"18.920000000","cityLongitude":"-99.230000000","cityId":1281,"isCapital":false,"stationName":"Cuernavaca","tourismURL":"www.sectur.gob.mx","tourismBoardName":"Mexico Ministry of Tourism","isDep":false,"timeZone":"-0600","isDST":"N","member":{"memId":179,"memName":"Mexico","shortMemName":"","url":"smn.cna.gob.mx","orgName":"Coordinaci\u00f3n General del Servicio Meteorol\u00f3gico Nacional","logo":"mexico_logo.jpg","ra":4},"forecast":{"issueDate":"N\/A","timeZone":"N\/A","forecastDay":[]},"climate":{"raintype":"Rainfall","raindef":"0.1","rainunit":"mm","datab":1971,"datae":2000,"tempb":"","tempe":"","rdayb":"","rdaye":"","rainfallb":"","rainfalle":"","climatefromclino":"","climateMonth":[{"month":1,"maxTemp":"25.0","minTemp":"12.3","meanTemp":null,"maxTempF":"77","minTempF":"54.1","meanTempF":null,"raindays":"1.2","rainfall":"13.3","climateFromMemDate":"2006-06-03"},{"month":2,"maxTemp":"26.3","minTemp":"13.2","meanTemp":null,"maxTempF":"79.3","minTempF":"55.8","meanTempF":null,"raindays":"1.3","rainfall":"4.2","climateFromMemDate":"2006-06-03"},{"month":3,"maxTemp":"28.6","minTemp":"14.9","meanTemp":null,"maxTempF":"83.5","minTempF":"58.8","meanTempF":null,"raindays":"1.2","rainfall":"5.7","climateFromMemDate":"2006-06-03"},{"month":4,"maxTemp":"29.7","minTemp":"16.5","meanTemp":null,"maxTempF":"85.5","minTempF":"61.7","meanTempF":null,"raindays":"3.1","rainfall":"16.4","climateFromMemDate":"2006-06-03"},{"month":5,"maxTemp":"29.6","minTemp":"17.5","meanTemp":null,"maxTempF":"85.3","minTempF":"63.5","meanTempF":null,"raindays":"8.6","rainfall":"58.9","climateFromMemDate":"2006-06-03"},{"month":6,"maxTemp":"26.6","minTemp":"16.9","meanTemp":null,"maxTempF":"79.9","minTempF":"62.4","meanTempF":null,"raindays":"19.1","rainfall":"250.3","climateFromMemDate":"2006-06-03"},{"month":7,"maxTemp":"25.8","minTemp":"15.9","meanTemp":null,"maxTempF":"78.4","minTempF":"60.6","meanTempF":null,"raindays":"20.1","rainfall":"260.7","climateFromMemDate":"2006-06-03"},{"month":8,"maxTemp":"25.6","minTemp":"15.9","meanTemp":null,"maxTempF":"78.1","minTempF":"60.6","meanTempF":null,"raindays":"20.8","rainfall":"266.9","climateFromMemDate":"2006-06-03"},{"month":9,"maxTemp":"24.7","minTemp":"15.7","meanTemp":null,"maxTempF":"76.5","minTempF":"60.3","meanTempF":null,"raindays":"19.4","rainfall":"255.7","climateFromMemDate":"2006-06-03"},{"month":10,"maxTemp":"25.5","minTemp":"14.9","meanTemp":null,"maxTempF":"77.9","minTempF":"58.8","meanTempF":null,"raindays":"9.2","rainfall":"109.6","climateFromMemDate":"2006-06-03"},{"month":11,"maxTemp":"25.8","minTemp":"13.8","meanTemp":null,"maxTempF":"78.4","minTempF":"56.8","meanTempF":null,"raindays":"2.4","rainfall":"16.8","climateFromMemDate":"2006-06-03"},{"month":12,"maxTemp":"25.3","minTemp":"12.8","meanTemp":null,"maxTempF":"77.5","minTempF":"55","meanTempF":null,"raindays":"1.1","rainfall":"7.1","climateFromMemDate":"2006-06-03"}]}}}