{"city":{"lang":"en","cityName":"Puerto Inirida","cityLatitude":"3.870000000","cityLongitude":"-67.920000000","cityId":1326,"isCapital":false,"stationName":"Puerto Inirida","tourismURL":"","tourismBoardName":"","isDep":false,"timeZone":"-0500","isDST":"N","member":{"memId":57,"memName":"Colombia","shortMemName":"","url":"www.ideam.gov.co","orgName":"Institute of Hydrology, Meteorology and Environment Studies","logo":"colombia_logo.png","ra":3},"forecast":{"issueDate":"N\/A","timeZone":"N\/A","forecastDay":[]},"climate":{"raintype":"N\/A","raindef":"","rainunit":"","datab":"","datae":"","tempb":"","tempe":"","rdayb":"","rdaye":"","rainfallb":"","rainfalle":"","climatefromclino":"","climateMonth":[]}}}