{"city":{"lang":"en","cityName":"Ludhiana","cityLatitude":"30.870000000","cityLongitude":"75.930000000","cityId":1604,"isCapital":false,"stationName":"Ludhiana","tourismURL":"","tourismBoardName":"","isDep":false,"timeZone":"+0530","isDST":"N","member":{"memId":66,"memName":"India","shortMemName":"","url":"mausam.imd.gov.in","orgName":"India Meteorological Department","logo":"india_logo.png","ra":2},"forecast":{"issueDate":"2024-07-19 15:00:00","timeZone":"Local","forecastDay":[{"forecastDate":"2024-07-20","wxdesc":"","weather":"Thundershowers","minTemp":"27","maxTemp":"38","minTempF":"81","maxTempF":"100","weatherIcon":202},{"forecastDate":"2024-07-21","wxdesc":"","weather":"Thundershowers","minTemp":"28","maxTemp":"37","minTempF":"82","maxTempF":"99","weatherIcon":202},{"forecastDate":"2024-07-22","wxdesc":"","weather":"Thundershowers","minTemp":"26","maxTemp":"34","minTempF":"79","maxTempF":"93","weatherIcon":202},{"forecastDate":"2024-07-23","wxdesc":"","weather":"Thundershowers","minTemp":"25","maxTemp":"34","minTempF":"77","maxTempF":"93","weatherIcon":202},{"forecastDate":"2024-07-24","wxdesc":"","weather":"Thunderstorms","minTemp":"26","maxTemp":"33","minTempF":"79","maxTempF":"91","weatherIcon":201},{"forecastDate":"2024-07-25","wxdesc":"","weather":"Thunderstorms","minTemp":"26","maxTemp":"33","minTempF":"79","maxTempF":"91","weatherIcon":201}]},"climate":{"raintype":"Rainfall","raindef":"","rainunit":"mm","datab":1961,"datae":1990,"tempb":"","tempe":"","rdayb":"","rdaye":"","rainfallb":"","rainfalle":"","climatefromclino":"","climateMonth":[{"month":1,"maxTemp":"19.7","minTemp":"6.2","meanTemp":null,"maxTempF":"67.5","minTempF":"43.2","meanTempF":null,"raindays":"2.9","rainfall":"30.6","climateFromMemDate":"2011-05-17"},{"month":2,"maxTemp":"22.4","minTemp":"8.4","meanTemp":null,"maxTempF":"72.3","minTempF":"47.1","meanTempF":null,"raindays":"3.5","rainfall":"34.1","climateFromMemDate":"2011-05-17"},{"month":3,"maxTemp":"28.3","minTemp":"13.1","meanTemp":null,"maxTempF":"82.9","minTempF":"55.6","meanTempF":null,"raindays":"4.8","rainfall":"28.7","climateFromMemDate":"2011-05-17"},{"month":4,"maxTemp":"35.2","minTemp":"18.8","meanTemp":null,"maxTempF":"95.4","minTempF":"65.8","meanTempF":null,"raindays":"3.9","rainfall":"14.9","climateFromMemDate":"2011-05-17"},{"month":5,"maxTemp":"40.2","minTemp":"23.9","meanTemp":null,"maxTempF":"104.4","minTempF":"75.0","meanTempF":null,"raindays":"3.9","rainfall":"14.7","climateFromMemDate":"2011-05-17"},{"month":6,"maxTemp":"40.7","minTemp":"27.1","meanTemp":null,"maxTempF":"105.3","minTempF":"80.8","meanTempF":null,"raindays":"4.5","rainfall":"52.0","climateFromMemDate":"2011-05-17"},{"month":7,"maxTemp":"35.9","minTemp":"26.7","meanTemp":null,"maxTempF":"96.6","minTempF":"80.1","meanTempF":null,"raindays":"11.9","rainfall":"200.2","climateFromMemDate":"2011-05-17"},{"month":8,"maxTemp":"34.4","minTemp":"25.9","meanTemp":null,"maxTempF":"93.9","minTempF":"78.6","meanTempF":null,"raindays":"10.7","rainfall":"174.3","climateFromMemDate":"2011-05-17"},{"month":9,"maxTemp":"34.7","minTemp":"23.7","meanTemp":null,"maxTempF":"94.5","minTempF":"74.7","meanTempF":null,"raindays":"5.7","rainfall":"108.4","climateFromMemDate":"2011-05-17"},{"month":10,"maxTemp":"33.3","minTemp":"17.6","meanTemp":null,"maxTempF":"91.9","minTempF":"63.7","meanTempF":null,"raindays":"1.1","rainfall":"19.8","climateFromMemDate":"2011-05-17"},{"month":11,"maxTemp":"27.7","minTemp":"10.6","meanTemp":null,"maxTempF":"81.9","minTempF":"51.1","meanTempF":null,"raindays":"1.5","rainfall":"5.4","climateFromMemDate":"2011-05-17"},{"month":12,"maxTemp":"21.9","minTemp":"6.6","meanTemp":null,"maxTempF":"71.4","minTempF":"43.9","meanTempF":null,"raindays":"2.1","rainfall":"15.6","climateFromMemDate":"2011-05-17"}]}}}