{"city":{"lang":"en","cityName":"Concepcion","cityLatitude":"-36.778330000","cityLongitude":"-73.062500000","cityId":2202,"isCapital":false,"stationName":"Concepcion","tourismURL":"","tourismBoardName":"","isDep":false,"timeZone":"-0400","isDST":"N","member":{"memId":28,"memName":"Chile","shortMemName":"","url":"www.meteochile.cl","orgName":"Direcci\u00f3n Meteorol\u00f3gica de Chile","logo":"chile_logo.png","ra":3},"forecast":{"issueDate":"2024-07-19 18:00:00","timeZone":"Local","forecastDay":[{"forecastDate":"2024-07-19","wxdesc":"","weather":"Sunny","minTemp":"4","maxTemp":"13","minTempF":"39","maxTempF":"55","weatherIcon":2402},{"forecastDate":"2024-07-20","wxdesc":"","weather":"Sunny","minTemp":"1","maxTemp":"13","minTempF":"34","maxTempF":"55","weatherIcon":2402},{"forecastDate":"2024-07-21","wxdesc":"","weather":"Sunny","minTemp":"1","maxTemp":"13","minTempF":"34","maxTempF":"55","weatherIcon":2402},{"forecastDate":"2024-07-22","wxdesc":"","weather":"Partly Cloudy","minTemp":"2","maxTemp":"12","minTempF":"36","maxTempF":"54","weatherIcon":2202},{"forecastDate":"2024-07-23","wxdesc":"","weather":"Overcast","minTemp":"4","maxTemp":"11","minTempF":"39","maxTempF":"52","weatherIcon":2001}]},"climate":{"raintype":"Rainfall","raindef":"0.1","rainunit":"mm","datab":1981,"datae":2010,"tempb":"","tempe":"","rdayb":"","rdaye":"","rainfallb":"","rainfalle":"","climatefromclino":"","climateMonth":[{"month":1,"maxTemp":"22.8","minTemp":"10.9","meanTemp":null,"maxTempF":"73.0","minTempF":"51.6","meanTempF":null,"raindays":"2","rainfall":"15.7","climateFromMemDate":"2017-01-11"},{"month":2,"maxTemp":"22.5","minTemp":"10.6","meanTemp":null,"maxTempF":"72.5","minTempF":"51.1","meanTempF":null,"raindays":"2","rainfall":"15.4","climateFromMemDate":"2017-01-11"},{"month":3,"maxTemp":"21.0","minTemp":"9.8","meanTemp":null,"maxTempF":"69.8","minTempF":"49.6","meanTempF":null,"raindays":"4","rainfall":"25.4","climateFromMemDate":"2017-01-11"},{"month":4,"maxTemp":"18.3","minTemp":"8.1","meanTemp":null,"maxTempF":"65.0","minTempF":"46.7","meanTempF":null,"raindays":"8","rainfall":"72.4","climateFromMemDate":"2017-01-11"},{"month":5,"maxTemp":"15.4","minTemp":"7.5","meanTemp":null,"maxTempF":"59.8","minTempF":"45.5","meanTempF":null,"raindays":"14","rainfall":"182.6","climateFromMemDate":"2017-01-11"},{"month":6,"maxTemp":"13.7","minTemp":"6.6","meanTemp":null,"maxTempF":"56.6","minTempF":"43.9","meanTempF":null,"raindays":"16","rainfall":"230.7","climateFromMemDate":"2017-01-11"},{"month":7,"maxTemp":"13.2","minTemp":"5.8","meanTemp":null,"maxTempF":"55.8","minTempF":"42.4","meanTempF":null,"raindays":"15","rainfall":"198.4","climateFromMemDate":"2017-01-11"},{"month":8,"maxTemp":"14.0","minTemp":"6.0","meanTemp":null,"maxTempF":"57.2","minTempF":"42.7","meanTempF":null,"raindays":"14","rainfall":"153.6","climateFromMemDate":"2017-01-11"},{"month":9,"maxTemp":"15.5","minTemp":"6.1","meanTemp":null,"maxTempF":"59.8","minTempF":"43.0","meanTempF":null,"raindays":"10","rainfall":"84.1","climateFromMemDate":"2017-01-11"},{"month":10,"maxTemp":"17.2","minTemp":"7.4","meanTemp":null,"maxTempF":"62.9","minTempF":"45.3","meanTempF":null,"raindays":"8","rainfall":"57.2","climateFromMemDate":"2017-01-11"},{"month":11,"maxTemp":"19.3","minTemp":"8.7","meanTemp":null,"maxTempF":"66.8","minTempF":"47.6","meanTempF":null,"raindays":"5","rainfall":"33.4","climateFromMemDate":"2017-01-11"},{"month":12,"maxTemp":"21.4","minTemp":"10.1","meanTemp":null,"maxTempF":"70.5","minTempF":"50.2","meanTempF":null,"raindays":"4","rainfall":"21.3","climateFromMemDate":"2017-01-11"}]}}}