{"city":{"lang":"en","cityName":"Aveiro","cityLatitude":"40.641300000","cityLongitude":"-8.653500000","cityId":2219,"isCapital":false,"stationName":"Aveiro","tourismURL":"","tourismBoardName":"","isDep":false,"timeZone":"+0100","isDST":"Y","member":{"memId":3,"memName":"Portugal","shortMemName":"","url":"www.ipma.pt","orgName":"Instituto Portugu\u00eas do Mar e da Atmosfera","logo":"portugal_logo.png","ra":6},"forecast":{"issueDate":"2024-07-19 14:31:02","timeZone":"Local","forecastDay":[{"forecastDate":"2024-07-19","wxdesc":"","weather":"Sunny Intervals","minTemp":"18","maxTemp":"23","minTempF":"64","maxTempF":"73","weatherIcon":2101},{"forecastDate":"2024-07-20","wxdesc":"","weather":"Rain","minTemp":"19","maxTemp":"25","minTempF":"66","maxTempF":"77","weatherIcon":1401},{"forecastDate":"2024-07-21","wxdesc":"","weather":"No Rain","minTemp":"18","maxTemp":"23","minTempF":"64","maxTempF":"73","weatherIcon":2102},{"forecastDate":"2024-07-22","wxdesc":"","weather":"No Rain","minTemp":"16","maxTemp":"26","minTempF":"61","maxTempF":"79","weatherIcon":2102},{"forecastDate":"2024-07-23","wxdesc":"","weather":"No Rain","minTemp":"17","maxTemp":"29","minTempF":"63","maxTempF":"84","weatherIcon":2102}]},"climate":{"raintype":"","raindef":"","rainunit":"","datab":1971,"datae":2000,"tempb":"","tempe":"","rdayb":"","rdaye":"","rainfallb":"","rainfalle":"","climatefromclino":"","climateMonth":[{"month":1,"maxTemp":"14.4","minTemp":"5.9","meanTemp":null,"maxTempF":"57.9","minTempF":"136.3","meanTempF":null,"raindays":null,"rainfall":"111.2","climateFromMemDate":"2018-01-10"},{"month":2,"maxTemp":"15.4","minTemp":"7.3","meanTemp":null,"maxTempF":"59.7","minTempF":"139.5","meanTempF":null,"raindays":null,"rainfall":"85.5","climateFromMemDate":"2018-01-10"},{"month":3,"maxTemp":"17.6","minTemp":"8.9","meanTemp":null,"maxTempF":"63.7","minTempF":"146.6","meanTempF":null,"raindays":null,"rainfall":"46.4","climateFromMemDate":"2018-01-10"},{"month":4,"maxTemp":"18.0","minTemp":"10.1","meanTemp":null,"maxTempF":"64.4","minTempF":"147.9","meanTempF":null,"raindays":null,"rainfall":"89.6","climateFromMemDate":"2018-01-10"},{"month":5,"maxTemp":"19.9","minTemp":"12.3","meanTemp":null,"maxTempF":"67.8","minTempF":"154.1","meanTempF":null,"raindays":null,"rainfall":"89.3","climateFromMemDate":"2018-01-10"},{"month":6,"maxTemp":"22.7","minTemp":"14.8","meanTemp":null,"maxTempF":"72.9","minTempF":"163.1","meanTempF":null,"raindays":null,"rainfall":"27.6","climateFromMemDate":"2018-01-10"},{"month":7,"maxTemp":"24.2","minTemp":"16.0","meanTemp":null,"maxTempF":"75.6","minTempF":"168.0","meanTempF":null,"raindays":null,"rainfall":"11.8","climateFromMemDate":"2018-01-10"},{"month":8,"maxTemp":"24.4","minTemp":"16.1","meanTemp":null,"maxTempF":"75.9","minTempF":"168.7","meanTempF":null,"raindays":null,"rainfall":"17.8","climateFromMemDate":"2018-01-10"},{"month":9,"maxTemp":"23.6","minTemp":"15.0","meanTemp":null,"maxTempF":"74.5","minTempF":"166.1","meanTempF":null,"raindays":null,"rainfall":"56.1","climateFromMemDate":"2018-01-10"},{"month":10,"maxTemp":"20.9","minTemp":"12.5","meanTemp":null,"maxTempF":"69.6","minTempF":"157.3","meanTempF":null,"raindays":null,"rainfall":"110.3","climateFromMemDate":"2018-01-10"},{"month":11,"maxTemp":"17.5","minTemp":"9.9","meanTemp":null,"maxTempF":"63.5","minTempF":"146.3","meanTempF":null,"raindays":null,"rainfall":"129.2","climateFromMemDate":"2018-01-10"},{"month":12,"maxTemp":"15.2","minTemp":"7.9","meanTemp":null,"maxTempF":"59.4","minTempF":"138.8","meanTempF":null,"raindays":null,"rainfall":"131.9","climateFromMemDate":"2018-01-10"}]}}}