{"city":{"lang":"en","cityName":"Nuwara Eliya","cityLatitude":"6.970000000","cityLongitude":"80.770000000","cityId":343,"isCapital":false,"stationName":"Nuwara Eliya","tourismURL":"www.srilankatourism.org","tourismBoardName":"Sri Lanka Tourist Board","isDep":false,"timeZone":"+0530","isDST":"N","member":{"memId":84,"memName":"Sri Lanka","shortMemName":"","url":"www.meteo.gov.lk","orgName":"National Meteorological Centre","logo":"sri_lanka_logo.png","ra":2},"forecast":{"issueDate":"2024-07-17 16:00:00","timeZone":"Local","forecastDay":[{"forecastDate":"2024-07-19","wxdesc":"","weather":"Isolated Showers","minTemp":"14","maxTemp":"17","minTempF":"57","maxTempF":"63","weatherIcon":1101},{"forecastDate":"2024-07-20","wxdesc":"","weather":"Fair","minTemp":"14","maxTemp":"18","minTempF":"57","maxTempF":"64","weatherIcon":2403}]},"climate":{"raintype":"Rainfall","raindef":"","rainunit":"mm","datab":1961,"datae":1990,"tempb":"","tempe":"","rdayb":"","rdaye":"","rainfallb":"","rainfalle":"","climatefromclino":"","climateMonth":[{"month":1,"maxTemp":"20.0","minTemp":"9.4","meanTemp":null,"maxTempF":"68.0","minTempF":"48.9","meanTempF":null,"raindays":"8","rainfall":"100.6","climateFromMemDate":"2002-01-03"},{"month":2,"maxTemp":"21.1","minTemp":"9.5","meanTemp":null,"maxTempF":"70.0","minTempF":"49.1","meanTempF":null,"raindays":"7","rainfall":"77.7","climateFromMemDate":"2002-01-03"},{"month":3,"maxTemp":"22.5","minTemp":"10.2","meanTemp":null,"maxTempF":"72.5","minTempF":"50.4","meanTempF":null,"raindays":"8","rainfall":"71.5","climateFromMemDate":"2002-01-03"},{"month":4,"maxTemp":"22.8","minTemp":"11.4","meanTemp":null,"maxTempF":"73.0","minTempF":"52.5","meanTempF":null,"raindays":"13","rainfall":"158.4","climateFromMemDate":"2002-01-03"},{"month":5,"maxTemp":"21.4","minTemp":"12.8","meanTemp":null,"maxTempF":"70.5","minTempF":"55.0","meanTempF":null,"raindays":"13","rainfall":"175.9","climateFromMemDate":"2002-01-03"},{"month":6,"maxTemp":"18.9","minTemp":"13.2","meanTemp":null,"maxTempF":"66.0","minTempF":"55.8","meanTempF":null,"raindays":"16","rainfall":"171.9","climateFromMemDate":"2002-01-03"},{"month":7,"maxTemp":"18.5","minTemp":"12.8","meanTemp":null,"maxTempF":"65.3","minTempF":"55.0","meanTempF":null,"raindays":"17","rainfall":"164.9","climateFromMemDate":"2002-01-03"},{"month":8,"maxTemp":"18.7","minTemp":"12.7","meanTemp":null,"maxTempF":"65.7","minTempF":"54.9","meanTempF":null,"raindays":"16","rainfall":"161.0","climateFromMemDate":"2002-01-03"},{"month":9,"maxTemp":"19.2","minTemp":"12.3","meanTemp":null,"maxTempF":"66.6","minTempF":"54.1","meanTempF":null,"raindays":"15","rainfall":"178.8","climateFromMemDate":"2002-01-03"},{"month":10,"maxTemp":"19.8","minTemp":"11.8","meanTemp":null,"maxTempF":"67.6","minTempF":"53.2","meanTempF":null,"raindays":"18","rainfall":"226.8","climateFromMemDate":"2002-01-03"},{"month":11,"maxTemp":"19.7","minTemp":"11.5","meanTemp":null,"maxTempF":"67.5","minTempF":"52.7","meanTempF":null,"raindays":"17","rainfall":"221.7","climateFromMemDate":"2002-01-03"},{"month":12,"maxTemp":"19.4","minTemp":"11.0","meanTemp":null,"maxTempF":"66.9","minTempF":"51.8","meanTempF":null,"raindays":"15","rainfall":"196.0","climateFromMemDate":"2002-01-03"}]}}}