{"city":{"lang":"en","cityName":"Johor Bahru","cityLatitude":"1.470000000","cityLongitude":"103.750000000","cityId":78,"isCapital":false,"stationName":"Johor Bahru","tourismURL":"tourism.gov.my","tourismBoardName":"Malaysia Tourism Promotion Board","isDep":false,"timeZone":"+0800","isDST":"N","member":{"memId":20,"memName":"Malaysia","shortMemName":"","url":"www.met.gov.my","orgName":"Malaysian Meteorological Department","logo":"malaysia_logo.png","ra":5},"forecast":{"issueDate":"2024-07-19 16:00:00","timeZone":"Local","forecastDay":[{"forecastDate":"2024-07-19","wxdesc":"","weather":"Rain","minTemp":"24","maxTemp":"33","minTempF":"75","maxTempF":"91","weatherIcon":1401},{"forecastDate":"2024-07-20","wxdesc":"","weather":"No Rain","minTemp":"24","maxTemp":"33","minTempF":"75","maxTempF":"91","weatherIcon":2102},{"forecastDate":"2024-07-21","wxdesc":"","weather":"Thunderstorms","minTemp":"24","maxTemp":"33","minTempF":"75","maxTempF":"91","weatherIcon":201},{"forecastDate":"2024-07-22","wxdesc":"","weather":"Thunderstorms","minTemp":"24","maxTemp":"33","minTempF":"75","maxTempF":"91","weatherIcon":201},{"forecastDate":"2024-07-23","wxdesc":"","weather":"Thunderstorms","minTemp":"24","maxTemp":"33","minTempF":"75","maxTempF":"91","weatherIcon":201}]},"climate":{"raintype":"Rainfall","raindef":"1","rainunit":"mm","datab":1974,"datae":2000,"tempb":"","tempe":"","rdayb":"","rdaye":"","rainfallb":"","rainfalle":"","climatefromclino":"","climateMonth":[{"month":1,"maxTemp":"31.0","minTemp":"21.9","meanTemp":null,"maxTempF":"87.8","minTempF":"71.4","meanTempF":null,"raindays":"11","rainfall":"162.6","climateFromMemDate":"2001-06-14"},{"month":2,"maxTemp":"32.0","minTemp":"22.0","meanTemp":null,"maxTempF":"89.6","minTempF":"71.6","meanTempF":null,"raindays":"9","rainfall":"139.8","climateFromMemDate":"2001-06-14"},{"month":3,"maxTemp":"32.5","minTemp":"22.4","meanTemp":null,"maxTempF":"90.5","minTempF":"72.3","meanTempF":null,"raindays":"13","rainfall":"203.4","climateFromMemDate":"2001-06-14"},{"month":4,"maxTemp":"32.8","minTemp":"22.9","meanTemp":null,"maxTempF":"91","minTempF":"73.2","meanTempF":null,"raindays":"15","rainfall":"232.8","climateFromMemDate":"2001-06-14"},{"month":5,"maxTemp":"32.5","minTemp":"23.1","meanTemp":null,"maxTempF":"90.5","minTempF":"73.6","meanTempF":null,"raindays":"15","rainfall":"215.3","climateFromMemDate":"2001-06-14"},{"month":6,"maxTemp":"32.1","minTemp":"22.9","meanTemp":null,"maxTempF":"89.8","minTempF":"73.2","meanTempF":null,"raindays":"12","rainfall":"148.1","climateFromMemDate":"2001-06-14"},{"month":7,"maxTemp":"31.5","minTemp":"22.4","meanTemp":null,"maxTempF":"88.7","minTempF":"72.3","meanTempF":null,"raindays":"13","rainfall":"177.0","climateFromMemDate":"2001-06-14"},{"month":8,"maxTemp":"31.5","minTemp":"22.4","meanTemp":null,"maxTempF":"88.7","minTempF":"72.3","meanTempF":null,"raindays":"13","rainfall":"185.9","climateFromMemDate":"2001-06-14"},{"month":9,"maxTemp":"31.5","minTemp":"22.4","meanTemp":null,"maxTempF":"88.7","minTempF":"72.3","meanTempF":null,"raindays":"13","rainfall":"190.8","climateFromMemDate":"2001-06-14"},{"month":10,"maxTemp":"31.8","minTemp":"22.6","meanTemp":null,"maxTempF":"89.2","minTempF":"72.7","meanTempF":null,"raindays":"16","rainfall":"217.7","climateFromMemDate":"2001-06-14"},{"month":11,"maxTemp":"31.3","minTemp":"22.7","meanTemp":null,"maxTempF":"88.3","minTempF":"72.9","meanTempF":null,"raindays":"17","rainfall":"237.6","climateFromMemDate":"2001-06-14"},{"month":12,"maxTemp":"30.6","minTemp":"22.4","meanTemp":null,"maxTempF":"87.1","minTempF":"72.3","meanTempF":null,"raindays":"15","rainfall":"244.5","climateFromMemDate":"2001-06-14"}]}}}