{"city":{"lang":"en","cityName":"Pittsburgh, Pennsylvania","cityLatitude":"40.500000000","cityLongitude":"-80.220000000","cityId":807,"isCapital":false,"stationName":"Pittsburgh","tourismURL":"","tourismBoardName":"","isDep":false,"timeZone":"-0400","isDST":"Y","member":{"memId":93,"memName":"United States of America","shortMemName":"","url":"www.nws.noaa.gov\/","orgName":"National Weather Service","logo":"usa_logo.png","ra":4},"forecast":{"issueDate":"2024-07-19 07:02:00","timeZone":"Local","forecastDay":[{"forecastDate":"2024-07-19","wxdesc":"","weather":"Sunny","minTemp":"","maxTemp":"29","minTempF":"","maxTempF":"85","weatherIcon":2402},{"forecastDate":"2024-07-20","wxdesc":"","weather":"Sunny Periods","minTemp":"18","maxTemp":"31","minTempF":"64","maxTempF":"88","weatherIcon":2201},{"forecastDate":"2024-07-21","wxdesc":"","weather":"Sunny","minTemp":"17","maxTemp":"32","minTempF":"63","maxTempF":"89","weatherIcon":2402},{"forecastDate":"2024-07-22","wxdesc":"","weather":"Hot","minTemp":"18","maxTemp":"33","minTempF":"65","maxTempF":"91","weatherIcon":3101},{"forecastDate":"2024-07-23","wxdesc":"","weather":"Thunderstorms","minTemp":"20","maxTemp":"31","minTempF":"68","maxTempF":"88","weatherIcon":201},{"forecastDate":"2024-07-24","wxdesc":"","weather":"Showers","minTemp":"21","maxTemp":"29","minTempF":"69","maxTempF":"85","weatherIcon":901},{"forecastDate":"2024-07-25","wxdesc":"","weather":"Showers","minTemp":"21","maxTemp":"28","minTempF":"69","maxTempF":"83","weatherIcon":901}]},"climate":{"raintype":"Rainfall","raindef":"","rainunit":"mm","datab":1981,"datae":2010,"tempb":"","tempe":"","rdayb":"","rdaye":"","rainfallb":"","rainfalle":"","climatefromclino":"","climateMonth":[{"month":1,"maxTemp":"2.1","minTemp":"-5.7","meanTemp":null,"maxTempF":"35.8","minTempF":"21.8","meanTempF":null,"raindays":null,"rainfall":"69.3","climateFromMemDate":"2014-01-06"},{"month":2,"maxTemp":"4.1","minTemp":"-4.4","meanTemp":null,"maxTempF":"39.3","minTempF":"24.0","meanTempF":null,"raindays":null,"rainfall":"68.1","climateFromMemDate":"2014-01-06"},{"month":3,"maxTemp":"9.4","minTemp":"-0.6","meanTemp":null,"maxTempF":"49.0","minTempF":"31.0","meanTempF":null,"raindays":null,"rainfall":"78.7","climateFromMemDate":"2014-01-06"},{"month":4,"maxTemp":"16.4","minTemp":"5.3","meanTemp":null,"maxTempF":"61.6","minTempF":"41.6","meanTempF":null,"raindays":null,"rainfall":"80.0","climateFromMemDate":"2014-01-06"},{"month":5,"maxTemp":"21.4","minTemp":"10.4","meanTemp":null,"maxTempF":"70.6","minTempF":"50.7","meanTempF":null,"raindays":null,"rainfall":"105.9","climateFromMemDate":"2014-01-06"},{"month":6,"maxTemp":"25.9","minTemp":"15.2","meanTemp":null,"maxTempF":"78.6","minTempF":"59.3","meanTempF":null,"raindays":null,"rainfall":"102.6","climateFromMemDate":"2014-01-06"},{"month":7,"maxTemp":"28.0","minTemp":"17.4","meanTemp":null,"maxTempF":"82.4","minTempF":"63.3","meanTempF":null,"raindays":null,"rainfall":"95.8","climateFromMemDate":"2014-01-06"},{"month":8,"maxTemp":"27.3","minTemp":"16.9","meanTemp":null,"maxTempF":"81.1","minTempF":"62.5","meanTempF":null,"raindays":null,"rainfall":"89.2","climateFromMemDate":"2014-01-06"},{"month":9,"maxTemp":"23.1","minTemp":"13.0","meanTemp":null,"maxTempF":"73.6","minTempF":"55.4","meanTempF":null,"raindays":null,"rainfall":"85.1","climateFromMemDate":"2014-01-06"},{"month":10,"maxTemp":"17.0","minTemp":"6.7","meanTemp":null,"maxTempF":"62.6","minTempF":"44.0","meanTempF":null,"raindays":null,"rainfall":"64.0","climateFromMemDate":"2014-01-06"},{"month":11,"maxTemp":"10.4","minTemp":"2.1","meanTemp":null,"maxTempF":"50.8","minTempF":"35.7","meanTempF":null,"raindays":null,"rainfall":"85.1","climateFromMemDate":"2014-01-06"},{"month":12,"maxTemp":"4.2","minTemp":"-3.1","meanTemp":null,"maxTempF":"39.5","minTempF":"26.4","meanTempF":null,"raindays":null,"rainfall":"74.2","climateFromMemDate":"2014-01-06"}]}}}