{"city":{"lang":"en","cityName":"Vologda","cityLatitude":"59.320000000","cityLongitude":"39.920000000","cityId":980,"isCapital":false,"stationName":"Vologda","tourismURL":"www.russiatourism.ru\/eng","tourismBoardName":"Tourism Department","isDep":false,"timeZone":"+0300","isDST":"N","member":{"memId":107,"memName":"Russian Federation","shortMemName":"","url":"www.meteorf.ru","orgName":"Russian Federal Service for Hydrometeorology and Environmental Monitoring","logo":"russian_logo.png","ra":2},"forecast":{"issueDate":"2024-07-19 18:05:00","timeZone":"Local","forecastDay":[{"forecastDate":"2024-07-20","wxdesc":"","weather":"Rain","minTemp":"14","maxTemp":"22","minTempF":"57","maxTempF":"72","weatherIcon":1401},{"forecastDate":"2024-07-21","wxdesc":"","weather":"Rain","minTemp":"15","maxTemp":"24","minTempF":"59","maxTempF":"75","weatherIcon":1401},{"forecastDate":"2024-07-22","wxdesc":"","weather":"Rain","minTemp":"13","maxTemp":"25","minTempF":"55","maxTempF":"77","weatherIcon":1401}]},"climate":{"raintype":"PPT","raindef":"","rainunit":"mm","datab":"","datae":"","tempb":"","tempe":"","rdayb":"","rdaye":"","rainfallb":"","rainfalle":"","climatefromclino":"","climateMonth":[{"month":1,"maxTemp":"-9.1","minTemp":"-16.9","meanTemp":null,"maxTempF":"15.6","minTempF":"1.6","meanTempF":null,"raindays":"10","rainfall":"32","climateFromMemDate":"2003-09-18"},{"month":2,"maxTemp":"-6.7","minTemp":"-14.8","meanTemp":null,"maxTempF":"19.9","minTempF":"5.4","meanTempF":null,"raindays":"8","rainfall":"25","climateFromMemDate":"2003-09-18"},{"month":3,"maxTemp":"-0.1","minTemp":"-8.8","meanTemp":null,"maxTempF":"31.8","minTempF":"16.2","meanTempF":null,"raindays":"8","rainfall":"26","climateFromMemDate":"2003-09-18"},{"month":4,"maxTemp":"7.9","minTemp":"-1.3","meanTemp":null,"maxTempF":"46.2","minTempF":"29.7","meanTempF":null,"raindays":"8","rainfall":"35","climateFromMemDate":"2003-09-18"},{"month":5,"maxTemp":"16.6","minTemp":"4.9","meanTemp":null,"maxTempF":"61.9","minTempF":"40.8","meanTempF":null,"raindays":"9","rainfall":"46","climateFromMemDate":"2003-09-18"},{"month":6,"maxTemp":"20.6","minTemp":"9.1","meanTemp":null,"maxTempF":"69.1","minTempF":"48.4","meanTempF":null,"raindays":"10","rainfall":"65","climateFromMemDate":"2003-09-18"},{"month":7,"maxTemp":"22.7","minTemp":"11.6","meanTemp":null,"maxTempF":"72.9","minTempF":"52.9","meanTempF":null,"raindays":"10","rainfall":"77","climateFromMemDate":"2003-09-18"},{"month":8,"maxTemp":"20.3","minTemp":"9.9","meanTemp":null,"maxTempF":"68.5","minTempF":"49.8","meanTempF":null,"raindays":"11","rainfall":"74","climateFromMemDate":"2003-09-18"},{"month":9,"maxTemp":"13.8","minTemp":"5.2","meanTemp":null,"maxTempF":"56.8","minTempF":"41.4","meanTempF":null,"raindays":"11","rainfall":"55","climateFromMemDate":"2003-09-18"},{"month":10,"maxTemp":"6.1","minTemp":"0.3","meanTemp":null,"maxTempF":"43.0","minTempF":"32.5","meanTempF":null,"raindays":"11","rainfall":"50","climateFromMemDate":"2003-09-18"},{"month":11,"maxTemp":"-1.0","minTemp":"-5.9","meanTemp":null,"maxTempF":"30.2","minTempF":"21.4","meanTempF":null,"raindays":"12","rainfall":"42","climateFromMemDate":"2003-09-18"},{"month":12,"maxTemp":"-5.9","minTemp":"-12.3","meanTemp":null,"maxTempF":"21.4","minTempF":"9.9","meanTempF":null,"raindays":"12","rainfall":"42","climateFromMemDate":"2003-09-18"}]}}}