{"city":{"lang":"en","cityName":"Kassel","cityLatitude":"51.300000000","cityLongitude":"9.450000000","cityId":1348,"isCapital":false,"stationName":"Kassel","tourismURL":"www.germany-tourism.de","tourismBoardName":"German National Tourist Board","isDep":false,"timeZone":"+0200","isDST":"Y","member":{"memId":16,"memName":"Germany","shortMemName":"","url":"www.dwd.de","orgName":"Deutscher Wetterdienst","logo":"germany_logo.png","ra":6},"forecast":{"issueDate":"2024-07-19 11:00:00","timeZone":"Local","forecastDay":[{"forecastDate":"2024-07-20","wxdesc":"","weather":"Partly Cloudy","minTemp":"14","maxTemp":"31","minTempF":"57","maxTempF":"88","weatherIcon":2202},{"forecastDate":"2024-07-21","wxdesc":"","weather":"Light Rain","minTemp":"17","maxTemp":"27","minTempF":"63","maxTempF":"81","weatherIcon":1502},{"forecastDate":"2024-07-22","wxdesc":"","weather":"Cloudy","minTemp":"16","maxTemp":"23","minTempF":"61","maxTempF":"73","weatherIcon":2301},{"forecastDate":"2024-07-23","wxdesc":"","weather":"Cloudy","minTemp":"13","maxTemp":"23","minTempF":"55","maxTempF":"73","weatherIcon":2301},{"forecastDate":"2024-07-24","wxdesc":"","weather":"Cloudy","minTemp":"13","maxTemp":"21","minTempF":"55","maxTempF":"70","weatherIcon":2301}]},"climate":{"raintype":"Rainfall","raindef":"1","rainunit":"mm","datab":1971,"datae":2000,"tempb":"","tempe":"","rdayb":"","rdaye":"","rainfallb":"","rainfalle":"","climatefromclino":"","climateMonth":[{"month":1,"maxTemp":"2.8","minTemp":"-1.5","meanTemp":null,"maxTempF":"37.0","minTempF":"29.3","meanTempF":null,"raindays":"10.7","rainfall":"53.5","climateFromMemDate":"2007-02-27"},{"month":2,"maxTemp":"4.2","minTemp":"-1.5","meanTemp":null,"maxTempF":"39.6","minTempF":"29.3","meanTempF":null,"raindays":"8.4","rainfall":"40.0","climateFromMemDate":"2007-02-27"},{"month":3,"maxTemp":"8.7","minTemp":"1.5","meanTemp":null,"maxTempF":"47.7","minTempF":"34.7","meanTempF":null,"raindays":"11.3","rainfall":"51.3","climateFromMemDate":"2007-02-27"},{"month":4,"maxTemp":"12.8","minTemp":"3.9","meanTemp":null,"maxTempF":"55.0","minTempF":"39.0","meanTempF":null,"raindays":"9.3","rainfall":"44.8","climateFromMemDate":"2007-02-27"},{"month":5,"maxTemp":"17.9","minTemp":"8.1","meanTemp":null,"maxTempF":"64.2","minTempF":"46.6","meanTempF":null,"raindays":"9.8","rainfall":"64.3","climateFromMemDate":"2007-02-27"},{"month":6,"maxTemp":"20.3","minTemp":"11.0","meanTemp":null,"maxTempF":"68.5","minTempF":"51.8","meanTempF":null,"raindays":"11.0","rainfall":"76.0","climateFromMemDate":"2007-02-27"},{"month":7,"maxTemp":"22.6","minTemp":"13.0","meanTemp":null,"maxTempF":"72.7","minTempF":"55.4","meanTempF":null,"raindays":"9.2","rainfall":"64.4","climateFromMemDate":"2007-02-27"},{"month":8,"maxTemp":"22.8","minTemp":"12.7","meanTemp":null,"maxTempF":"73.0","minTempF":"54.9","meanTempF":null,"raindays":"8.8","rainfall":"56.6","climateFromMemDate":"2007-02-27"},{"month":9,"maxTemp":"18.4","minTemp":"9.8","meanTemp":null,"maxTempF":"65.1","minTempF":"49.6","meanTempF":null,"raindays":"9.3","rainfall":"57.1","climateFromMemDate":"2007-02-27"},{"month":10,"maxTemp":"13.0","minTemp":"5.9","meanTemp":null,"maxTempF":"55.4","minTempF":"42.6","meanTempF":null,"raindays":"9.3","rainfall":"51.8","climateFromMemDate":"2007-02-27"},{"month":11,"maxTemp":"6.7","minTemp":"2.1","meanTemp":null,"maxTempF":"44.1","minTempF":"35.8","meanTempF":null,"raindays":"10.9","rainfall":"59.3","climateFromMemDate":"2007-02-27"},{"month":12,"maxTemp":"3.9","minTemp":"-0.2","meanTemp":null,"maxTempF":"39.0","minTempF":"31.6","meanTempF":null,"raindays":"12.5","rainfall":"67.0","climateFromMemDate":"2007-02-27"}]}}}