{"city":{"lang":"en","cityName":"Baku","cityLatitude":"40.380000000","cityLongitude":"49.850000000","cityId":18,"isCapital":true,"stationName":"Baku","tourismURL":"","tourismBoardName":"","isDep":false,"timeZone":"+0400","isDST":"N","member":{"memId":7,"memName":"Azerbaijan","shortMemName":"","url":"www.eco.gov.az","orgName":"National Hydrometeorological Department","logo":"azerbaijan_logo.png","ra":6},"forecast":{"issueDate":"2024-07-19 10:46:00","timeZone":"Local","forecastDay":[{"forecastDate":"2024-07-19","wxdesc":"","weather":"Partly Cloudy","minTemp":"25","maxTemp":"36","minTempF":"77","maxTempF":"97","weatherIcon":2202},{"forecastDate":"2024-07-20","wxdesc":"","weather":"No Rain","minTemp":"24","maxTemp":"36","minTempF":"75","maxTempF":"97","weatherIcon":2102},{"forecastDate":"2024-07-21","wxdesc":"","weather":"No Rain","minTemp":"25","maxTemp":"36","minTempF":"77","maxTempF":"97","weatherIcon":2102}]},"climate":{"raintype":"PPT","raindef":"","rainunit":"mm","datab":1971,"datae":1990,"tempb":"","tempe":"","rdayb":"","rdaye":"","rainfallb":"","rainfalle":"","climatefromclino":"","climateMonth":[{"month":1,"maxTemp":"6.6","minTemp":"2.1","meanTemp":null,"maxTempF":"43.9","minTempF":"35.8","meanTempF":null,"raindays":"6","rainfall":"21","climateFromMemDate":"2001-04-23"},{"month":2,"maxTemp":"6.3","minTemp":"2.0","meanTemp":null,"maxTempF":"43.3","minTempF":"35.6","meanTempF":null,"raindays":"6","rainfall":"20","climateFromMemDate":"2001-04-23"},{"month":3,"maxTemp":"9.8","minTemp":"4.2","meanTemp":null,"maxTempF":"49.6","minTempF":"39.6","meanTempF":null,"raindays":"5","rainfall":"21","climateFromMemDate":"2001-04-23"},{"month":4,"maxTemp":"16.4","minTemp":"9.4","meanTemp":null,"maxTempF":"61.5","minTempF":"48.9","meanTempF":null,"raindays":"4","rainfall":"18","climateFromMemDate":"2001-04-23"},{"month":5,"maxTemp":"22.1","minTemp":"14.9","meanTemp":null,"maxTempF":"71.8","minTempF":"58.8","meanTempF":null,"raindays":"3","rainfall":"18","climateFromMemDate":"2001-04-23"},{"month":6,"maxTemp":"27.3","minTemp":"19.7","meanTemp":null,"maxTempF":"81.1","minTempF":"67.5","meanTempF":null,"raindays":"2","rainfall":"8","climateFromMemDate":"2001-04-23"},{"month":7,"maxTemp":"30.6","minTemp":"22.2","meanTemp":null,"maxTempF":"87.1","minTempF":"72.0","meanTempF":null,"raindays":"1","rainfall":"2","climateFromMemDate":"2001-04-23"},{"month":8,"maxTemp":"29.7","minTemp":"22.9","meanTemp":null,"maxTempF":"85.5","minTempF":"73.2","meanTempF":null,"raindays":"2","rainfall":"6","climateFromMemDate":"2001-04-23"},{"month":9,"maxTemp":"25.6","minTemp":"19.4","meanTemp":null,"maxTempF":"78.1","minTempF":"66.9","meanTempF":null,"raindays":"2","rainfall":"15","climateFromMemDate":"2001-04-23"},{"month":10,"maxTemp":"19.6","minTemp":"13.6","meanTemp":null,"maxTempF":"67.3","minTempF":"56.5","meanTempF":null,"raindays":"6","rainfall":"25","climateFromMemDate":"2001-04-23"},{"month":11,"maxTemp":"13.5","minTemp":"8.8","meanTemp":null,"maxTempF":"56.3","minTempF":"47.8","meanTempF":null,"raindays":"6","rainfall":"30","climateFromMemDate":"2001-04-23"},{"month":12,"maxTemp":"9.7","minTemp":"4.8","meanTemp":null,"maxTempF":"49.5","minTempF":"40.6","meanTempF":null,"raindays":"6","rainfall":"26","climateFromMemDate":"2001-04-23"}]}}}