{"city":{"lang":"en","cityName":"Pokhara","cityLatitude":"28.210000000","cityLongitude":"84.000000000","cityId":2104,"isCapital":false,"stationName":"Pokhara","tourismURL":"","tourismBoardName":"","isDep":false,"timeZone":"+0545","isDST":"N","member":{"memId":31,"memName":"Nepal","shortMemName":"","url":"www.dhm.gov.np\/","orgName":"Department of Hydrology and meteorology","logo":"nepal_logo.png","ra":2},"forecast":{"issueDate":"2024-07-18 18:00:00","timeZone":"Local","forecastDay":[{"forecastDate":"2024-07-19","wxdesc":"","weather":"Rain","minTemp":"23","maxTemp":"31","minTempF":"73","maxTempF":"88","weatherIcon":1401}]},"climate":{"raintype":"Rainfall","raindef":"0.1","rainunit":"mm","datab":1981,"datae":2010,"tempb":"","tempe":"","rdayb":"","rdaye":"","rainfallb":"","rainfalle":"","climatefromclino":"","climateMonth":[{"month":1,"maxTemp":"19.7","minTemp":"7.1","meanTemp":null,"maxTempF":"67.5","minTempF":"44.8","meanTempF":null,"raindays":"29","rainfall":"23.1","climateFromMemDate":"2016-09-15"},{"month":2,"maxTemp":"22.2","minTemp":"9.2","meanTemp":null,"maxTempF":"72.0","minTempF":"48.6","meanTempF":null,"raindays":"28","rainfall":"34.6","climateFromMemDate":"2016-09-15"},{"month":3,"maxTemp":"26.7","minTemp":"12.8","meanTemp":null,"maxTempF":"80.1","minTempF":"55.0","meanTempF":null,"raindays":"31","rainfall":"60.0","climateFromMemDate":"2016-09-15"},{"month":4,"maxTemp":"29.8","minTemp":"15.7","meanTemp":null,"maxTempF":"85.6","minTempF":"60.3","meanTempF":null,"raindays":"30","rainfall":"127.6","climateFromMemDate":"2016-09-15"},{"month":5,"maxTemp":"30.1","minTemp":"18.4","meanTemp":null,"maxTempF":"86.2","minTempF":"65.1","meanTempF":null,"raindays":"31","rainfall":"359.2","climateFromMemDate":"2016-09-15"},{"month":6,"maxTemp":"30.6","minTemp":"20.9","meanTemp":null,"maxTempF":"87.1","minTempF":"69.6","meanTempF":null,"raindays":"30","rainfall":"669.0","climateFromMemDate":"2016-09-15"},{"month":7,"maxTemp":"30.0","minTemp":"22.0","meanTemp":null,"maxTempF":"86.0","minTempF":"71.6","meanTempF":null,"raindays":"31","rainfall":"940.3","climateFromMemDate":"2016-09-15"},{"month":8,"maxTemp":"30.2","minTemp":"22.0","meanTemp":null,"maxTempF":"86.4","minTempF":"71.6","meanTempF":null,"raindays":"31","rainfall":"866.3","climateFromMemDate":"2016-09-15"},{"month":9,"maxTemp":"29.3","minTemp":"20.8","meanTemp":null,"maxTempF":"84.7","minTempF":"69.4","meanTempF":null,"raindays":"30","rainfall":"640.8","climateFromMemDate":"2016-09-15"},{"month":10,"maxTemp":"27.5","minTemp":"16.7","meanTemp":null,"maxTempF":"81.5","minTempF":"62.1","meanTempF":null,"raindays":"31","rainfall":"139.7","climateFromMemDate":"2016-09-15"},{"month":11,"maxTemp":"24.1","minTemp":"11.9","meanTemp":null,"maxTempF":"75.4","minTempF":"53.4","meanTempF":null,"raindays":"25","rainfall":"17.8","climateFromMemDate":"2016-09-15"},{"month":12,"maxTemp":"20.7","minTemp":"8.0","meanTemp":null,"maxTempF":"69.3","minTempF":"46.4","meanTempF":null,"raindays":"20","rainfall":"21.7","climateFromMemDate":"2016-09-15"}]}}}