{"city":{"lang":"en","cityName":"Galle","cityLatitude":"6.030000000","cityLongitude":"80.220000000","cityId":340,"isCapital":false,"stationName":"Galle","tourismURL":"www.srilankatourism.org","tourismBoardName":"Sri Lanka Tourist Board","isDep":false,"timeZone":"+0530","isDST":"N","member":{"memId":84,"memName":"Sri Lanka","shortMemName":"","url":"www.meteo.gov.lk","orgName":"National Meteorological Centre","logo":"sri_lanka_logo.png","ra":2},"forecast":{"issueDate":"2024-07-17 16:00:00","timeZone":"Local","forecastDay":[{"forecastDate":"2024-07-19","wxdesc":"","weather":"Showers","minTemp":"25","maxTemp":"30","minTempF":"77","maxTempF":"86","weatherIcon":901},{"forecastDate":"2024-07-20","wxdesc":"","weather":"Isolated Showers","minTemp":"25","maxTemp":"30","minTempF":"77","maxTempF":"86","weatherIcon":1101}]},"climate":{"raintype":"Rainfall","raindef":"","rainunit":"mm","datab":1961,"datae":1990,"tempb":"","tempe":"","rdayb":"","rdaye":"","rainfallb":"","rainfalle":"","climatefromclino":"","climateMonth":[{"month":1,"maxTemp":"29.0","minTemp":"22.8","meanTemp":null,"maxTempF":"84.2","minTempF":"73.0","meanTempF":null,"raindays":"8","rainfall":"85.1","climateFromMemDate":"2002-01-03"},{"month":2,"maxTemp":"29.0","minTemp":"23.0","meanTemp":null,"maxTempF":"84.2","minTempF":"73.4","meanTempF":null,"raindays":"6","rainfall":"70.5","climateFromMemDate":"2002-01-03"},{"month":3,"maxTemp":"29.9","minTemp":"23.9","meanTemp":null,"maxTempF":"85.8","minTempF":"75.0","meanTempF":null,"raindays":"9","rainfall":"111.3","climateFromMemDate":"2002-01-03"},{"month":4,"maxTemp":"30.6","minTemp":"24.8","meanTemp":null,"maxTempF":"87.1","minTempF":"76.6","meanTempF":null,"raindays":"12","rainfall":"206.8","climateFromMemDate":"2002-01-03"},{"month":5,"maxTemp":"30.6","minTemp":"25.5","meanTemp":null,"maxTempF":"87.1","minTempF":"77.9","meanTempF":null,"raindays":"16","rainfall":"290.4","climateFromMemDate":"2002-01-03"},{"month":6,"maxTemp":"29.8","minTemp":"25.2","meanTemp":null,"maxTempF":"85.6","minTempF":"77.4","meanTempF":null,"raindays":"17","rainfall":"188.2","climateFromMemDate":"2002-01-03"},{"month":7,"maxTemp":"29.0","minTemp":"24.8","meanTemp":null,"maxTempF":"84.2","minTempF":"76.6","meanTempF":null,"raindays":"16","rainfall":"163.2","climateFromMemDate":"2002-01-03"},{"month":8,"maxTemp":"28.6","minTemp":"24.7","meanTemp":null,"maxTempF":"83.5","minTempF":"76.5","meanTempF":null,"raindays":"16","rainfall":"185.9","climateFromMemDate":"2002-01-03"},{"month":9,"maxTemp":"28.4","minTemp":"24.7","meanTemp":null,"maxTempF":"83.1","minTempF":"76.5","meanTempF":null,"raindays":"18","rainfall":"255.8","climateFromMemDate":"2002-01-03"},{"month":10,"maxTemp":"28.5","minTemp":"24.1","meanTemp":null,"maxTempF":"83.3","minTempF":"75.4","meanTempF":null,"raindays":"18","rainfall":"322.7","climateFromMemDate":"2002-01-03"},{"month":11,"maxTemp":"28.7","minTemp":"23.5","meanTemp":null,"maxTempF":"83.7","minTempF":"74.3","meanTempF":null,"raindays":"16","rainfall":"321.0","climateFromMemDate":"2002-01-03"},{"month":12,"maxTemp":"29.1","minTemp":"23.1","meanTemp":null,"maxTempF":"84.4","minTempF":"73.6","meanTempF":null,"raindays":"12","rainfall":"176.9","climateFromMemDate":"2002-01-03"}]}}}