{"city":{"lang":"en","cityName":"Halls Creek","cityLatitude":"-18.230000000","cityLongitude":"127.660000000","cityId":412,"isCapital":false,"stationName":"HALLS CREEK AIRPORT","tourismURL":"www.tourism.australia.com","tourismBoardName":"Australian Tourist Commission","isDep":false,"timeZone":"+0800","isDST":"N","member":{"memId":185,"memName":"Australia","shortMemName":"","url":"www.bom.gov.au","orgName":"Bureau of Meteorology","logo":"australia_logo.png","ra":5},"forecast":{"issueDate":"2024-07-19 16:36:10","timeZone":"Local","forecastDay":[{"forecastDate":"2024-07-19","wxdesc":"","weather":"Clear","minTemp":"","maxTemp":"","minTempF":"","maxTempF":"","weatherIcon":2502},{"forecastDate":"2024-07-20","wxdesc":"","weather":"Sunny","minTemp":"5","maxTemp":"27","minTempF":"41","maxTempF":"81","weatherIcon":2402},{"forecastDate":"2024-07-21","wxdesc":"","weather":"Sunny","minTemp":"8","maxTemp":"26","minTempF":"46","maxTempF":"79","weatherIcon":2402},{"forecastDate":"2024-07-22","wxdesc":"","weather":"Sunny","minTemp":"8","maxTemp":"26","minTempF":"46","maxTempF":"79","weatherIcon":2402},{"forecastDate":"2024-07-23","wxdesc":"","weather":"Sunny","minTemp":"8","maxTemp":"27","minTempF":"46","maxTempF":"81","weatherIcon":2402},{"forecastDate":"2024-07-24","wxdesc":"","weather":"Sunny","minTemp":"8","maxTemp":"29","minTempF":"46","maxTempF":"84","weatherIcon":2402},{"forecastDate":"2024-07-25","wxdesc":"","weather":"Partly Cloudy","minTemp":"10","maxTemp":"29","minTempF":"50","maxTempF":"84","weatherIcon":2202},{"forecastDate":"2024-07-26","wxdesc":"","weather":"Partly Cloudy","minTemp":"11","maxTemp":"28","minTempF":"52","maxTempF":"82","weatherIcon":2202}]},"climate":{"raintype":"Rainfall","raindef":"","rainunit":"mm","datab":1981,"datae":2010,"tempb":"","tempe":"","rdayb":"","rdaye":"","rainfallb":"","rainfalle":"","climatefromclino":"","climateMonth":[{"month":1,"maxTemp":"36.6","minTemp":"24.4","meanTemp":null,"maxTempF":"97.9","minTempF":"75.9","meanTempF":null,"raindays":"14.3","rainfall":"164.9","climateFromMemDate":"2002-03-23"},{"month":2,"maxTemp":"35.4","minTemp":"23.9","meanTemp":null,"maxTempF":"95.7","minTempF":"75.0","meanTempF":null,"raindays":"13.3","rainfall":"161.7","climateFromMemDate":"2002-03-23"},{"month":3,"maxTemp":"35.1","minTemp":"23.0","meanTemp":null,"maxTempF":"95.2","minTempF":"73.4","meanTempF":null,"raindays":"8.7","rainfall":"101.4","climateFromMemDate":"2002-03-23"},{"month":4,"maxTemp":"33.8","minTemp":"20.7","meanTemp":null,"maxTempF":"92.8","minTempF":"69.3","meanTempF":null,"raindays":"2.2","rainfall":"19.2","climateFromMemDate":"2002-03-23"},{"month":5,"maxTemp":"30.2","minTemp":"17.1","meanTemp":null,"maxTempF":"86.4","minTempF":"62.8","meanTempF":null,"raindays":"1.6","rainfall":"9.0","climateFromMemDate":"2002-03-23"},{"month":6,"maxTemp":"27.1","minTemp":"13.9","meanTemp":null,"maxTempF":"80.8","minTempF":"57.0","meanTempF":null,"raindays":"0.9","rainfall":"6.7","climateFromMemDate":"2002-03-23"},{"month":7,"maxTemp":"27.3","minTemp":"13.1","meanTemp":null,"maxTempF":"81.1","minTempF":"55.6","meanTempF":null,"raindays":"0.8","rainfall":"5.5","climateFromMemDate":"2002-03-23"},{"month":8,"maxTemp":"30.1","minTemp":"15.2","meanTemp":null,"maxTempF":"86.2","minTempF":"59.4","meanTempF":null,"raindays":"0.3","rainfall":"0.6","climateFromMemDate":"2002-03-23"},{"month":9,"maxTemp":"34.5","minTemp":"19.8","meanTemp":null,"maxTempF":"94.1","minTempF":"67.6","meanTempF":null,"raindays":"1.0","rainfall":"5.2","climateFromMemDate":"2002-03-23"},{"month":10,"maxTemp":"37.3","minTemp":"23.0","meanTemp":null,"maxTempF":"99.1","minTempF":"73.4","meanTempF":null,"raindays":"3.4","rainfall":"18.2","climateFromMemDate":"2002-03-23"},{"month":11,"maxTemp":"38.4","minTemp":"24.8","meanTemp":null,"maxTempF":"101.1","minTempF":"76.6","meanTempF":null,"raindays":"6.7","rainfall":"45.1","climateFromMemDate":"2002-03-23"},{"month":12,"maxTemp":"37.5","minTemp":"24.9","meanTemp":null,"maxTempF":"99.5","minTempF":"76.8","meanTempF":null,"raindays":"11.3","rainfall":"98.3","climateFromMemDate":"2002-03-23"}]}}}