{"city":{"lang":"en","cityName":"Dodoma","cityLatitude":"-6.162959000","cityLongitude":"35.751606900","cityId":667,"isCapital":true,"stationName":"Dodoma","tourismURL":"www.tanzania-web.com","tourismBoardName":"Tanzania Tourist Board","isDep":false,"timeZone":"+0300","isDST":"N","member":{"memId":49,"memName":"United Republic of Tanzania","shortMemName":"","url":"www.meteo.go.tz","orgName":"Tanzania Meteorological Agency","logo":"tanzania_logo.png","ra":1},"forecast":{"issueDate":"2024-07-19 15:00:00","timeZone":"Local","forecastDay":[{"forecastDate":"2024-07-20","wxdesc":"","weather":"Partly Cloudy","minTemp":"15","maxTemp":"28","minTempF":"59","maxTempF":"82","weatherIcon":2202},{"forecastDate":"2024-07-21","wxdesc":"","weather":"Partly Cloudy","minTemp":"15","maxTemp":"28","minTempF":"59","maxTempF":"82","weatherIcon":2202},{"forecastDate":"2024-07-22","wxdesc":"","weather":"Partly Cloudy","minTemp":"15","maxTemp":"28","minTempF":"59","maxTempF":"82","weatherIcon":2202},{"forecastDate":"2024-07-23","wxdesc":"","weather":"Partly Cloudy","minTemp":"15","maxTemp":"28","minTempF":"59","maxTempF":"82","weatherIcon":2202},{"forecastDate":"2024-07-24","wxdesc":"","weather":"Partly Cloudy","minTemp":"15","maxTemp":"27","minTempF":"59","maxTempF":"81","weatherIcon":2202}]},"climate":{"raintype":"Rainfall","raindef":"1","rainunit":"mm","datab":1971,"datae":2000,"tempb":"","tempe":"","rdayb":"","rdaye":"","rainfallb":"","rainfalle":"","climatefromclino":"","climateMonth":[{"month":1,"maxTemp":"29.4","minTemp":"18.6","meanTemp":null,"maxTempF":"84.9","minTempF":"65.5","meanTempF":null,"raindays":"10","rainfall":"133.70","climateFromMemDate":"2011-01-03"},{"month":2,"maxTemp":"29.4","minTemp":"18.6","meanTemp":null,"maxTempF":"84.9","minTempF":"65.5","meanTempF":null,"raindays":"9","rainfall":"144.50","climateFromMemDate":"2011-01-03"},{"month":3,"maxTemp":"29.0","minTemp":"18.3","meanTemp":null,"maxTempF":"84.2","minTempF":"64.9","meanTempF":null,"raindays":"7","rainfall":"113.90","climateFromMemDate":"2011-01-03"},{"month":4,"maxTemp":"28.7","minTemp":"17.9","meanTemp":null,"maxTempF":"83.7","minTempF":"64.2","meanTempF":null,"raindays":"5","rainfall":"57.80","climateFromMemDate":"2011-01-03"},{"month":5,"maxTemp":"28.0","minTemp":"16.5","meanTemp":null,"maxTempF":"82.4","minTempF":"61.7","meanTempF":null,"raindays":"1","rainfall":"5.30","climateFromMemDate":"2011-01-03"},{"month":6,"maxTemp":"27.1","minTemp":"14.4","meanTemp":null,"maxTempF":"80.8","minTempF":"57.9","meanTempF":null,"raindays":"0","rainfall":"0.10","climateFromMemDate":"2011-01-03"},{"month":7,"maxTemp":"26.5","minTemp":"13.6","meanTemp":null,"maxTempF":"79.7","minTempF":"56.5","meanTempF":null,"raindays":"0","rainfall":"0.03","climateFromMemDate":"2011-01-03"},{"month":8,"maxTemp":"27.3","minTemp":"14.2","meanTemp":null,"maxTempF":"81.1","minTempF":"57.6","meanTempF":null,"raindays":"0","rainfall":"0.01","climateFromMemDate":"2011-01-03"},{"month":9,"maxTemp":"29.0","minTemp":"15.3","meanTemp":null,"maxTempF":"84.2","minTempF":"59.5","meanTempF":null,"raindays":"0","rainfall":"0.01","climateFromMemDate":"2011-01-03"},{"month":10,"maxTemp":"30.5","minTemp":"16.9","meanTemp":null,"maxTempF":"86.9","minTempF":"62.4","meanTempF":null,"raindays":"0","rainfall":"2.08","climateFromMemDate":"2011-01-03"},{"month":11,"maxTemp":"30.1","minTemp":"18.3","meanTemp":null,"maxTempF":"86.2","minTempF":"64.9","meanTempF":null,"raindays":"2","rainfall":"26.25","climateFromMemDate":"2011-01-03"},{"month":12,"maxTemp":"30.4","minTemp":"18.8","meanTemp":null,"maxTempF":"86.7","minTempF":"65.8","meanTempF":null,"raindays":"7","rainfall":"123.28","climateFromMemDate":"2011-01-03"}]}}}